coder_mcp/__init__.py
coder_mcp/ai/__init__.py
coder_mcp/ai/enhancers/README.md
coder_mcp/ai/enhancers/__init__.py
coder_mcp/ai/enhancers/base_enhancer.py
coder_mcp/ai/enhancers/code_enhancer.py
coder_mcp/ai/enhancers/context_enhancer.py
coder_mcp/ai/enhancers/dependency_enhancer.py
coder_mcp/ai/enhancers/enhancer_orchestrator.py
coder_mcp/ai/enhancers/generation_enhancer.py
coder_mcp/ai/enhancers/search_enhancer.py
coder_mcp/ai/models/__init__.py
coder_mcp/ai/models/metrics.py
coder_mcp/ai/models/responses.py
coder_mcp/ai/models/types.py
coder_mcp/ai/openai_service.py
coder_mcp/ai/processors/__init__.py
coder_mcp/ai/processors/base.py
coder_mcp/ai/processors/change_processor.py
coder_mcp/ai/processors/code_processor.py
coder_mcp/ai/processors/markdown_processor.py
coder_mcp/ai/processors/response_builder.py
coder_mcp/ai/prompts.py
coder_mcp/ai/services/__init__.py
coder_mcp/ai/services/base.py
coder_mcp/ai/services/completions.py
coder_mcp/ai/services/embeddings.py
coder_mcp/analysis/__init__.py
coder_mcp/analysis/analysis_result.py
coder_mcp/analysis/analyzer_factory.py
coder_mcp/analysis/base_analyzer.py
coder_mcp/analysis/dependency_analyzer.py
coder_mcp/analysis/detectors/__init__.py
coder_mcp/analysis/detectors/base.py
coder_mcp/analysis/detectors/code_smells/__init__.py
coder_mcp/analysis/detectors/code_smells/complexity.py
coder_mcp/analysis/detectors/code_smells/coordinator.py
coder_mcp/analysis/detectors/code_smells/quality.py
coder_mcp/analysis/detectors/code_smells/structural.py
coder_mcp/analysis/detectors/code_smells/utils.py
coder_mcp/analysis/detectors/constants.py
coder_mcp/analysis/detectors/duplicates/__init__.py
coder_mcp/analysis/detectors/duplicates/block_extractor.py
coder_mcp/analysis/detectors/duplicates/coordinator.py
coder_mcp/analysis/detectors/duplicates/report_generator.py
coder_mcp/analysis/detectors/duplicates/similarity_calculator.py
coder_mcp/analysis/detectors/duplicates/statistics_calculator.py
coder_mcp-1.0.1.dist-info/LICENSE
coder_mcp-1.0.1.dist-info/METADATA
coder_mcp-1.0.1.dist-info/WHEEL
coder_mcp-1.0.1.dist-info/entry_points.txt
coder_mcp-1.0.1.dist-info/RECORD
