Metadata-Version: 2.3
Name: coder-mcp
Version: 1.0.1
Summary: High‑performance Managed Code Processor (MCP) server with AI‑powered code analysis and editing.
License: MIT
Author: Chris Baker
Author-email: csbaker80@gmail.com
Requires-Python: >=3.10,<3.14
Classifier: License :: OSI Approved :: MIT License
Classifier: Programming Language :: Python :: 3
Classifier: Programming Language :: Python :: 3.10
Classifier: Programming Language :: Python :: 3.11
Classifier: Programming Language :: Python :: 3.12
Classifier: Programming Language :: Python :: 3.13
Classifier: Topic :: Software Development :: Code Generators
Requires-Dist: aiofiles (>=23.0.0)
Requires-Dist: astroid (>=3.0.0)
Requires-Dist: chardet (>=5.0.0)
Requires-Dist: click (>=8.1.0)
Requires-Dist: defusedxml (>=0.7.0)
Requires-Dist: diff-match-patch (>=20230430)
Requires-Dist: fastapi (>=0.104.0)
Requires-Dist: hiredis (>=2.3.0)
Requires-Dist: hnswlib (>=0.8.0)
Requires-Dist: jinja2 (>=3.1.0)
Requires-Dist: mcp (>=1.10.0)
Requires-Dist: numpy (>=1.24.0)
Requires-Dist: openai (>=1.0.0)
Requires-Dist: packaging (>=23.0)
Requires-Dist: pydantic (>=2.0.0)
Requires-Dist: python-dotenv (>=1.0.0)
Requires-Dist: python-levenshtein (>=0.23.0)
Requires-Dist: redis (>=5.0.0)
Requires-Dist: rich (>=13.0.0)
Requires-Dist: sentence-transformers (>=2.2.0)
Requires-Dist: toml (>=0.10.2)
Requires-Dist: transformers (>=4.30.0)
Requires-Dist: tree-sitter (>=0.20.4)
Project-URL: Issues, https://github.com/coder-mcp/coder-mcp/issues
Project-URL: Source, https://github.com/coder-mcp/coder-mcp
